tensorflow_text/__init__.py
tensorflow_text/python/__init__.py
tensorflow_text/python/keras/__init__.py
tensorflow_text/python/keras/layers/__init__.py
tensorflow_text/python/keras/layers/todense.py
tensorflow_text/python/keras/layers/tokenization_layers.py
tensorflow_text/python/metrics/__init__.py
tensorflow_text/python/metrics/_text_similarity_metric_ops.so
tensorflow_text/python/metrics/text_similarity_metric_ops.py
tensorflow_text/python/numpy/__init__.py
tensorflow_text/python/numpy/viterbi_decode.py
tensorflow_text/python/ops/__init__.py
tensorflow_text/python/ops/_boise_offset_converter.so
tensorflow_text/python/ops/_byte_splitter.so
tensorflow_text/python/ops/_constrained_sequence_op.so
tensorflow_text/python/ops/_fast_bert_normalizer.so
tensorflow_text/python/ops/_fast_sentencepiece_tokenizer.so
tensorflow_text/python/ops/_fast_wordpiece_tokenizer.so
tensorflow_text/python/ops/_mst_ops.so
tensorflow_text/python/ops/_ngrams_op.so
tensorflow_text/python/ops/_normalize_ops.so
tensorflow_text/python/ops/_phrase_tokenizer.so
tensorflow_text/python/ops/_regex_split_ops.so
tensorflow_text/python/ops/_sentence_breaking_ops.so
tensorflow_text/python/ops/_sentencepiece_tokenizer.so
tensorflow_text/python/ops/_split_merge_from_logits_tokenizer.so
tensorflow_text/python/ops/_split_merge_tokenizer.so
tensorflow_text/python/ops/_state_based_sentence_breaker_op.so
tensorflow_text/python/ops/_trimmer_ops.so
tensorflow_text/python/ops/_unicode_script_tokenizer.so
tensorflow_text/python/ops/_utf8_binarize_op.so
tensorflow_text/python/ops/_whitespace_tokenizer.so
tensorflow_text/python/ops/_whitespace_tokenizer_v2.so
tensorflow_text/python/ops/_wordpiece_tokenizer.so
tensorflow_text/python/ops/bert_tokenizer.py
tensorflow_text/python/ops/boise_offset_converter.py
tensorflow_text/python/ops/byte_splitter.py
tensorflow_text/python/ops/create_feature_bitmask_op.py
tensorflow_text/python/ops/fast_bert_normalizer.py
tensorflow_text_nightly-2.20.0.dev20250619.dist-info/METADATA
tensorflow_text_nightly-2.20.0.dev20250619.dist-info/WHEEL
tensorflow_text_nightly-2.20.0.dev20250619.dist-info/top_level.txt
tensorflow_text_nightly-2.20.0.dev20250619.dist-info/RECORD
tensorflow_text_nightly-2.20.0.dev20250619.dist-info/licenses/LICENSE
