Metadata-Version: 2.1
Name: tensorflow-text-nightly
Version: 2.20.0.dev20250619
Summary: TF.Text is a TensorFlow library of text related ops, modules, and subgraphs.
Home-page: http://github.com/tensorflow/text
Author: Google Inc.
Author-email: packages@tensorflow.org
License: Apache 2.0
Keywords: tensorflow text machine learning
Classifier: Development Status :: 3 - Alpha
Classifier: Intended Audience :: Developers
Classifier: Intended Audience :: Education
Classifier: Intended Audience :: Science/Research
Classifier: License :: OSI Approved :: Apache Software License
Classifier: Programming Language :: Python :: 3
Classifier: Programming Language :: Python :: 3.9
Classifier: Programming Language :: Python :: 3.10
Classifier: Programming Language :: Python :: 3.11
Classifier: Programming Language :: Python :: 3.12
Classifier: Programming Language :: Python :: 3 :: Only
Classifier: Topic :: Scientific/Engineering
Classifier: Topic :: Scientific/Engineering :: Artificial Intelligence
Classifier: Topic :: Software Development
Classifier: Topic :: Software Development :: Libraries
Classifier: Topic :: Software Development :: Libraries :: Python Modules
License-File: LICENSE
Provides-Extra: tests
Requires-Dist: absl-py; extra == "tests"
Requires-Dist: pytest; extra == "tests"
Requires-Dist: tensorflow-datasets>=3.2.0; extra == "tests"
